sql_generator/QueryObjects.py
sql_generator/__init__.py
sql_generator/select_query_generator.py
sql_query_builder_py-0.1.0.dist-info/licenses/LICENSE
sql_query_builder_py-0.1.0.dist-info/METADATA
sql_query_builder_py-0.1.0.dist-info/WHEEL
sql_query_builder_py-0.1.0.dist-info/top_level.txt
sql_query_builder_py-0.1.0.dist-info/RECORD
