Metadata-Version: 2.4
Name: sql-query-builder-py
Version: 0.1.0
Summary: Dynamically generate SQL queries
Author-email: Arthur Murat <66724813+arthurm040@users.noreply.github.com>
License: MIT
Requires-Python: >=3.12
License-File: LICENSE
Dynamic: license-file
